MANIFEST.in
requirements.txt
setup.cfg
setup.py
napalm_exos/__init__.py
napalm_exos/exos.py
napalm_exos.egg-info/PKG-INFO
napalm_exos.egg-info/SOURCES.txt
napalm_exos.egg-info/dependency_links.txt
napalm_exos.egg-info/requires.txt
napalm_exos.egg-info/top_level.txt
napalm_exos/templates/set_hostname.j2
napalm_exos/utils/__init__.py
test/__init__.py
test/unit/TestDriver.py
test/unit/__init__.py
test/unit/conftest.py
test/unit/test_getters.py